Metadata-Version: 2.4
Name: stindex
Version: 1.0.2
Summary: Spatiotemporal Index Extraction from Unstructured Text
Author-email: Wenxiao Zhang <wenxiao.zhang@research.uwa.edu.au>
License: MIT
Project-URL: Homepage, https://github.com/MoeBuTa/STIndex/
Project-URL: Documentation, https://stindex.readthedocs.io
Project-URL: Repository, https://github.com/MoeBuTa/STIndex/
Project-URL: Bug Tracker, https://github.com/MoeBuTa/STIndex/issues
Keywords: nlp,spatiotemporal,information-extraction,ner,geocoding,temporal-extraction
Classifier: Development Status :: 3 - Alpha
Classifier: Intended Audience :: Developers
Classifier: Intended Audience :: Science/Research
Classifier: License :: OSI Approved :: MIT License
Classifier: Programming Language :: Python :: 3
Classifier: Programming Language :: Python :: 3.9
Classifier: Programming Language :: Python :: 3.10
Classifier: Programming Language :: Python :: 3.11
Classifier: Topic :: Scientific/Engineering :: Information Analysis
Classifier: Topic :: Text Processing :: Linguistic
Requires-Python: >=3.9
License-File: LICENSE
Requires-Dist: instructor>=1.0.0
Requires-Dist: openai>=1.0.0
Requires-Dist: anthropic>=0.18.0
Requires-Dist: pydantic<2.12,>=2.0.0
Requires-Dist: spacy>=3.7.0
Requires-Dist: dateparser>=1.2.0
Requires-Dist: pendulum>=3.0.0
Requires-Dist: geopy>=2.4.0
Requires-Dist: folium>=0.20.0
Requires-Dist: geopandas>=0.14.0
Requires-Dist: pandas>=2.0.0
Requires-Dist: numpy<2.0,>=1.26.0
Requires-Dist: unstructured[local-inference]>=0.10.0
Requires-Dist: beautifulsoup4>=4.12.0
Requires-Dist: nltk>=3.8.0
Requires-Dist: rich>=13.0.0
Requires-Dist: typer>=0.9.0
Requires-Dist: python-dotenv>=1.0.0
Requires-Dist: loguru>=0.7.0
Requires-Dist: pyyaml
Requires-Dist: transformers>=4.30.0
Requires-Dist: torch>=2.0.0
Requires-Dist: accelerate>=0.25.0
Requires-Dist: deepspeed>=0.14.0
Requires-Dist: tqdm>=4.65.0
Requires-Dist: datasets>=3.0.0
Requires-Dist: vllm>=0.11.0
Requires-Dist: opencv-python-headless>=4.11.0
Requires-Dist: fastapi>=0.100.0
Requires-Dist: uvicorn>=0.20.0
Requires-Dist: ms-swift
Requires-Dist: addict>=2.4.0
Requires-Dist: mcp>=1.2.0
Requires-Dist: matplotlib>=3.7.0
Requires-Dist: seaborn>=0.12.0
Requires-Dist: plotly>=5.17.0
Requires-Dist: pytest>=7.4.0
Requires-Dist: pytest-cov>=4.1.0
Requires-Dist: black>=23.0.0
Requires-Dist: isort>=5.12.0
Requires-Dist: flake8>=6.0.0
Requires-Dist: mypy>=1.5.0
Requires-Dist: gdown
Dynamic: license-file
